Workbook

Sheet Assumptions
A1: Country | B1: Revenue Growth % | C1: COGS % | D1: OPEX % | E1: Tax Rate % | F1: FX Rate (to USD)
A2: USA | B2: 0.05 | C2: 0.6 | D2: 0.25 | E2: 0.21 | F2: 1
A3: Germany | B3: 0.04 | C3: 0.62 | D3: 0.27 | E3: 0.3 | F3: 0.92
A4: India | B4: 0.08 | C4: 0.55 | D4: 0.2 | E4: 0.25 | F4: 0.012
A7: Country | B7: Opening Debt | C7: Interest Rate % | D7: Principal Repayment FY25 | E7: Principal Repayment FY26 | F7: Principal Repayment FY27
A8: USA | B8: 500000 | C8: 0.05 | D8: 100000 | E8: 150000 | F8: 250000
A9: Germany | B9: 400000 | C9: 0.045 | D9: 80000 | E9: 100000 | F9: 220000
A10: India | B10: 1000000 | C10: 0.06 | D10: 200000 | E10: 300000 | F10: 400000
A12: Country | B12: FY25 | C12: FY26 | D12: FY27
A13: USA | B13: 50000 | C13: 60000 | D13: 70000
A14: Germany | B14: 40000 | C14: 45000 | D14: 50000
A15: India | B15: 70000 | C15: 80000 | D15: 90000
A17: Metric | B17: Value | D17: Country | E17: CapEx % of Revenue
A18: DSO (Days) | B18: 45 | D18: USA | E18: 0.08
A19: DPO (Days) | B19: 30 | D19: Germany | E19: 0.07
A20: Inventory Days | B20: 60 | D20: India | E20: 0.1
A22: Scenario | B22: Revenue Adjustment | C22: OPEX Adjustment | D22: COGS Adjustment
A23: Base | B23: 1 | C23: 1 | D23: 1
A24: Optimistic | B24: 1.05 | C24: 0.95 | D24: 0.98
A25: Pessimistic | B25: 0.95 | C25: 1.05 | D25: 1.02

Sheet Historical Data
A1: Country | B1: Year | C1: Revenue | D1: COGS | E1: OPEX | F1: EBIT | G1: Interest | H1: Tax | I1: Net Income | J1: Cash | K1: AR | L1: Inventory | M1: AP | N1: Debt | O1: Equity | P1: FX Rate
A2: USA | B2: FY22 | C2: 1000000 | D2: 600000 | E2: 250000 | F2: =C2-D2-E2 -> 150000 | G2: 25000 | H2: =F2-G2*0.21 -> 144750 | I2: =F2-G2-H2 -> -19750 | J2: 200000 | K2: =C2/365*45 -> 123287.67 | L2: =D2/365*60 -> 98630.137 | M2: =D2/365*30 -> 49315.068 | N2: 500000 | O2: 500000 | P2: 1
A3: USA | B3: FY23 | C3: 1050000 | D3: 630000 | E3: 262500 | F3: =C3-D3-E3 -> 157500 | G3: 25000 | H3: =F3-G3*0.21 -> 152250 | I3: =F3-G3-H3 -> -19750 | J3: 210000 | K3: =C3/365*45 -> 129452.05 | L3: =D3/365*60 -> 103561.64 | M3: =D3/365*30 -> 51780.822 | N3: 500000 | O3: 520000 | P3: 1
A4: USA | B4: FY24 | C4: 1100000 | D4: 660000 | E4: 275000 | F4: =C4-D4-E4 -> 165000 | G4: 25000 | H4: =F4-G4*0.21 -> 159750 | I4: =F4-G4-H4 -> -19750 | J4: 220000 | K4: =C4/365*45 -> 135616.44 | L4: =D4/365*60 -> 108493.15 | M4: =D4/365*30 -> 54246.575 | N4: 500000 | O4: 540000 | P4: 1
A5: Germany | B5: FY22 | C5: 800000 | D5: 496000 | E5: 216000 | F5: =C5-D5-E5 -> 88000 | G5: 20000 | H5: =F5-G5*0.3 -> 82000 | I5: =F5-G5-H5 -> -14000 | J5: 150000 | K5: =C5/365*45 -> 98630.137 | L5: =D5/365*60 -> 81534.247 | M5: =D5/365*30 -> 40767.123 | N5: 400000 | O5: 400000 | P5: 0.92
A6: Germany | B6: FY23 | C6: 832000 | D6: 515840 | E6: 230000 | F6: =C6-D6-E6 -> 86160 | G6: 20000 | H6: =F6-G6*0.3 -> 80160 | I6: =F6-G6-H6 -> -14000 | J6: 155000 | K6: =C6/365*45 -> 102575.34 | L6: =D6/365*60 -> 84795.616 | M6: =D6/365*30 -> 42397.808 | N6: 400000 | O6: 420000 | P6: 0.92
A7: Germany | B7: FY24 | C7: 865000 | D7: 536300 | E7: 245000 | F7: =C7-D7-E7 -> 83700 | G7: 20000 | H7: =F7-G7*0.3 -> 77700 | I7: =F7-G7-H7 -> -14000 | J7: 160000 | K7: =C7/365*45 -> 106643.84 | L7: =D7/365*60 -> 88158.904 | M7: =D7/365*30 -> 44079.452 | N7: 400000 | O7: 440000 | P7: 0.92
A8: India | B8: FY22 | C8: 1200000 | D8: 660000 | E8: 240000 | F8: =C8-D8-E8 -> 300000 | G8: 30000 | H8: =F8-G8*0.25 -> 292500 | I8: =F8-G8-H8 -> -22500 | J8: 250000 | K8: =C8/365*45 -> 147945.21 | L8: =D8/365*60 -> 108493.15 | M8: =D8/365*30 -> 54246.575 | N8: 1000000 | O8: 500000 | P8: 0.012
A9: India | B9: FY23 | C9: 1296000 | D9: 712800 | E9: 259200 | F9: =C9-D9-E9 -> 324000 | G9: 30000 | H9: =F9-G9*0.25 -> 316500 | I9: =F9-G9-H9 -> -22500 | J9: 260000 | K9: =C9/365*45 -> 159780.82 | L9: =D9/365*60 -> 117172.6 | M9: =D9/365*30 -> 58586.301 | N9: 1000000 | O9: 520000 | P9: 0.012
A10: India | B10: FY24 | C10: 1400000 | D10: 770000 | E10: 280000 | F10: =C10-D10-E10 -> 350000 | G10: 30000 | H10: =F10-G10*0.25 -> 342500 | I10: =F10-G10-H10 -> -22500 | J10: 270000 | K10: =C10/365*45 -> 172602.74 | L10: =D10/365*60 -> 126575.34 | M10: =D10/365*30 -> 63287.671 | N10: 1000000 | O10: 540000 | P10: 0.012

Sheet Country P&L Forecast
A1: Key | B1: Country | C1: Year | D1: Revenue | E1: COGS | F1: OPEX | G1: EBIT | H1: Interest | I1: Tax | J1: Net Income | K1: FX Rate | L1: Revenue (USD) | M1: Net Income (USD)
A2: =B2&C2 -> USAFY25 | B2: USA | C2: FY25 | D2: =1100000*1.05 -> 1155000 | E2: =D2*0.6 -> 693000 | F2: =D2*0.25 -> 288750 | G2: =D2-E2-F2 -> 173250 | H2: 25000 | I2: =(G2-H2)*0.21 -> 31132.5 | J2: =G2-H2-I2 -> 117117.5 | K2: 1 | L2: =D2*K2 -> 1155000 | M2: =J2*K2 -> 117117.5
A3: =B3&C3 -> USAFY26 | B3: USA | C3: FY26 | D3: =D2*1.05 -> 1212750 | E3: =D3*0.6 -> 727650 | F3: =D3*0.25 -> 303187.5 | G3: =D3-E3-F3 -> 181912.5 | H3: 25000 | I3: =(G3-H3)*0.21 -> 32951.625 | J3: =G3-H3-I3 -> 123960.88 | K3: 1 | L3: =D3*K3 -> 1212750 | M3: =J3*K3 -> 123960.88
A4: =B4&C4 -> USAFY27 | B4: USA | C4: FY27 | D4: =D3*1.05 -> 1273387.5 | E4: =D4*0.6 -> 764032.5 | F4: =D4*0.25 -> 318346.88 | G4: =D4-E4-F4 -> 191008.12 | H4: 25000 | I4: =(G4-H4)*0.21 -> 34861.706 | J4: =G4-H4-I4 -> 131146.42 | K4: 1 | L4: =D4*K4 -> 1273387.5 | M4: =J4*K4 -> 131146.42
A5: =B5&C5 -> GermanyFY25 | B5: Germany | C5: FY25 | D5: =865000*1.04 -> 899600 | E5: =D5*0.62 -> 557752 | F5: =D5*0.27 -> 242892 | G5: =D5-E5-F5 -> 98956 | H5: 20000 | I5: =(G5-H5)*0.3 -> 23686.8 | J5: =G5-H5-I5 -> 55269.2 | K5: 0.92 | L5: =D5*K5 -> 827632 | M5: =J5*K5 -> 50847.664
A6: =B6&C6 -> GermanyFY26 | B6: Germany | C6: FY26 | D6: =D5*1.04 -> 935584 | E6: =D6*0.62 -> 580062.08 | F6: =D6*0.27 -> 252607.68 | G6: =D6-E6-F6 -> 102914.24 | H6: 20000 | I6: =(G6-H6)*0.3 -> 24874.272 | J6: =G6-H6-I6 -> 58039.968 | K6: 0.92 | L6: =D6*K6 -> 860737.28 | M6: =J6*K6 -> 53396.771
A7: =B7&C7 -> GermanyFY27 | B7: Germany | C7: FY27 | D7: =D6*1.04 -> 973007.36 | E7: =D7*0.62 -> 603264.56 | F7: =D7*0.27 -> 262711.99 | G7: =D7-E7-F7 -> 107030.81 | H7: 20000 | I7: =(G7-H7)*0.3 -> 26109.243 | J7: =G7-H7-I7 -> 60921.567 | K7: 0.92 | L7: =D7*K7 -> 895166.77 | M7: =J7*K7 -> 56047.841
A8: =B8&C8 -> IndiaFY25 | B8: India | C8: FY25 | D8: =1400000*1.08 -> 1512000 | E8: =D8*0.55 -> 831600 | F8: =D8*0.2 -> 302400 | G8: =D8-E8-F8 -> 378000 | H8: 30000 | I8: =(G8-H8)*0.25 -> 87000 | J8: =G8-H8-I8 -> 261000 | K8: 0.012 | L8: =D8*K8 -> 18144 | M8: =J8*K8 -> 3132
A9: =B9&C9 -> IndiaFY26 | B9: India | C9: FY26 | D9: =D8*1.08 -> 1632960 | E9: =D9*0.55 -> 898128 | F9: =D9*0.2 -> 326592 | G9: =D9-E9-F9 -> 408240 | H9: 30000 | I9: =(G9-H9)*0.25 -> 94560 | J9: =G9-H9-I9 -> 283680 | K9: 0.012 | L9: =D9*K9 -> 19595.52 | M9: =J9*K9 -> 3404.16
A10: =B10&C10 -> IndiaFY27 | B10: India | C10: FY27 | D10: =D9*1.08 -> 1763596.8 | E10: =D10*0.55 -> 969978.24 | F10: =D10*0.2 -> 352719.36 | G10: =D10-E10-F10 -> 440899.2 | H10: 30000 | I10: =(G10-H10)*0.25 -> 102724.8 | J10: =G10-H10-I10 -> 308174.4 | K10: 0.012 | L10: =D10*K10 -> 21163.162 | M10: =J10*K10 -> 3698.0928

Sheet Country BS Forecast
A1: Country | B1: Year | C1: Cash | D1: AR | E1: Inventory | F1: AP | G1: Debt | H1: Equity | I1: Total Assets | J1: Liabilities + Equity
A2: USA | B2: FY25 | C2: ='Historical Data'!J4+'Country P&L Forecast'!J2-Assumptions!D8 -> 237117.5 | D2: =(VLOOKUP(A2&B2, 'Country P&L Forecast'!A:D, 4, FALSE) / 365) * Assumptions!$B$18 -> 142397.26 | E2: ='Country P&L Forecast'!E2/365*Assumptions!$B$20 -> 113917.81 | F2: ='Country P&L Forecast'!E2/365*Assumptions!$B$19 -> 56958.904 | G2: =Assumptions!B8-Assumptions!D8 -> 400000 | H2: ='Historical Data'!O4+'Country P&L Forecast'!J2 -> 657117.5 | I2: =C2+D2+E2 -> 493432.57 | J2: =SUM(F2:H2) -> 1114076.4
A3: USA | B3: FY26 | C3: =C2+'Country P&L Forecast'!J3-Assumptions!E8 -> 211078.38 | D3: =(VLOOKUP(A3&B3, 'Country P&L Forecast'!A:D, 4, FALSE) / 365) * Assumptions!$B$18 -> 149517.12 | E3: ='Country P&L Forecast'!E3/365*Assumptions!$B$20 -> 119613.7 | F3: ='Country P&L Forecast'!E3/365*Assumptions!$B$19 -> 59806.849 | G3: =G2-Assumptions!E8 -> 250000 | H3: =H2+'Country P&L Forecast'!J3 -> 781078.38 | I3: =C3+D3+E3 -> 480209.2 | J3: =SUM(F3:H3) -> 1090885.2
A4: USA | B4: FY27 | C4: =C3+'Country P&L Forecast'!J4-Assumptions!F8 -> 92224.794 | D4: =(VLOOKUP(A4&B4, 'Country P&L Forecast'!A:D, 4, FALSE) / 365) * Assumptions!$B$18 -> 156992.98 | E4: ='Country P&L Forecast'!E4/365*Assumptions!$B$20 -> 125594.38 | F4: ='Country P&L Forecast'!E4/365*Assumptions!$B$19 -> 62797.192 | G4: =G3-Assumptions!F8 -> 0 | H4: =H3+'Country P&L Forecast'!J4 -> 912224.79 | I4: =C4+D4+E4 -> 374812.16 | J4: =SUM(F4:H4) -> 975021.99
A5: Germany | B5: FY25 | C5: ='Historical Data'!J7+'Country P&L Forecast'!J5-Assumptions!D9 -> 135269.2 | D5: =(VLOOKUP(A5&B5, 'Country P&L Forecast'!A:D, 4, FALSE) / 365) * Assumptions!$B$18 -> 110909.59 | E5: ='Country P&L Forecast'!E5/365*Assumptions!$B$20 -> 91685.26 | F5: ='Country P&L Forecast'!E5/365*Assumptions!$B$19 -> 45842.63 | G5: =Assumptions!B9-Assumptions!D9 -> 320000 | H5: ='Historical Data'!O7+'Country P&L Forecast'!J5 -> 495269.2 | I5: =C5+D5+E5 -> 337864.05 | J5: =SUM(F5:H5) -> 861111.83
A6: Germany | B6: FY26 | C6: =C5+'Country P&L Forecast'!J6-Assumptions!E9 -> 93309.168 | D6: =(VLOOKUP(A6&B6, 'Country P&L Forecast'!A:D, 4, FALSE) / 365) * Assumptions!$B$18 -> 115345.97 | E6: ='Country P&L Forecast'!E6/365*Assumptions!$B$20 -> 95352.671 | F6: ='Country P&L Forecast'!E6/365*Assumptions!$B$19 -> 47676.335 | G6: =G5-Assumptions!E9 -> 220000 | H6: =H5+'Country P&L Forecast'!J6 -> 553309.17 | I6: =C6+D6+E6 -> 304007.81 | J6: =SUM(F6:H6) -> 820985.5
A7: Germany | B7: FY27 | C7: =C6+'Country P&L Forecast'!J7-Assumptions!F9 -> -65769.265 | D7: =(VLOOKUP(A7&B7, 'Country P&L Forecast'!A:D, 4, FALSE) / 365) * Assumptions!$B$18 -> 119959.81 | E7: ='Country P&L Forecast'!E7/365*Assumptions!$B$20 -> 99166.778 | F7: ='Country P&L Forecast'!E7/365*Assumptions!$B$19 -> 49583.389 | G7: =G6-Assumptions!F9 -> 0 | H7: =H6+'Country P&L Forecast'!J7 -> 614230.73 | I7: =C7+D7+E7 -> 153357.32 | J7: =SUM(F7:H7) -> 663814.12
A8: India | B8: FY25 | C8: ='Historical Data'!J10+'Country P&L Forecast'!J8-Assumptions!D10 -> 331000 | D8: =(VLOOKUP(A8&B8, 'Country P&L Forecast'!A:D, 4, FALSE) / 365) * Assumptions!$B$18 -> 186410.96 | E8: ='Country P&L Forecast'!E8/365*Assumptions!$B$20 -> 136701.37 | F8: ='Country P&L Forecast'!E8/365*Assumptions!$B$19 -> 68350.685 | G8: =Assumptions!B10-Assumptions!D10 -> 800000 | H8: ='Historical Data'!O10+'Country P&L Forecast'!J8 -> 801000 | I8: =C8+D8+E8 -> 654112.33 | J8: =SUM(F8:H8) -> 1669350.7
A9: India | B9: FY26 | C9: =C8+'Country P&L Forecast'!J9-Assumptions!E10 -> 314680 | D9: =(VLOOKUP(A9&B9, 'Country P&L Forecast'!A:D, 4, FALSE) / 365) * Assumptions!$B$18 -> 201323.84 | E9: ='Country P&L Forecast'!E9/365*Assumptions!$B$20 -> 147637.48 | F9: ='Country P&L Forecast'!E9/365*Assumptions!$B$19 -> 73818.74 | G9: =G8-Assumptions!E10 -> 500000 | H9: =H8+'Country P&L Forecast'!J9 -> 1084680 | I9: =C9+D9+E9 -> 663641.32 | J9: =SUM(F9:H9) -> 1658498.7
A10: India | B10: FY27 | C10: =C9+'Country P&L Forecast'!J10-Assumptions!F10 -> 222854.4 | D10: =(VLOOKUP(A10&B10, 'Country P&L Forecast'!A:D, 4, FALSE) / 365) * Assumptions!$B$18 -> 217429.74 | E10: ='Country P&L Forecast'!E10/365*Assumptions!$B$20 -> 159448.48 | F10: ='Country P&L Forecast'!E10/365*Assumptions!$B$19 -> 79724.239 | G10: =G9-Assumptions!F10 -> 100000 | H10: =H9+'Country P&L Forecast'!J10 -> 1392854.4 | I10: =C10+D10+E10 -> 599732.62 | J10: =SUM(F10:H10) -> 1572578.6

Sheet Country CashFlow Forecast
A1: Country | B1: Year | C1: Net Income | D1: Change in AR | E1: Change in Inventory | F1: Change in AP | G1: CapEx | H1: Net Cash Flow | I1: Net Income FX-Adjusted | J1: Change in AR FX-Adjusted | K1: Change in Inventory FX-Adjusted | L1: Change in AP FX-Adjusted | M1: CapEX | O1: Country | P1: FX_to_USD
A2: USA | B2: FY25 | C2: =VLOOKUP(A2&B2,'Country P&L Forecast'!A2:J10,10,FALSE) -> 117117.5 | D2: ='Country BS Forecast'!D2-'Historical Data'!K4 -> 6780.8219 | E2: ='Country BS Forecast'!E2-'Historical Data'!L4 -> 5424.6575 | F2: ='Country BS Forecast'!F2-'Historical Data'!M4 -> 2712.3288 | G2: ='Country P&L Forecast'!D2*Assumptions!$E$18 -> 92400 | H2: =C2-D2-E2+F2-G2 -> 15224.349 | I2: =C2*$P$2 -> 117117.5 | J2: =D2*$P$2 -> 6780.8219 | K2: =E2*$P$2 -> 5424.6575 | L2: =F2*$P$2 -> 2712.3288 | M2: =G2*$P$2 -> 92400 | O2: USA | P2: =INDEX(Assumptions!$F:$F,MATCH(O2,Assumptions!$A:$A,0)) -> 1
A3: USA | B3: FY26 | C3: =VLOOKUP(A3&B3,'Country P&L Forecast'!A3:J11,10,FALSE) -> 123960.88 | D3: ='Country BS Forecast'!D3-'Country BS Forecast'!D2 -> 7119.863 | E3: ='Country BS Forecast'!E3-'Country BS Forecast'!E2 -> 5695.8904 | F3: ='Country BS Forecast'!F3-'Country BS Forecast'!F2 -> 2847.9452 | G3: ='Country P&L Forecast'!D3*Assumptions!$E$18 -> 97020 | H3: =C3-D3-E3+F3-G3 -> 16973.067 | I3: =C3*$P$2 -> 123960.88 | J3: =D3*$P$2 -> 7119.863 | K3: =E3*$P$2 -> 5695.8904 | L3: =F3*$P$2 -> 2847.9452 | M3: =G3*$P$2 -> 97020 | O3: Germany | P3: =INDEX(Assumptions!$F:$F,MATCH(O3,Assumptions!$A:$A,0)) -> 0.92
A4: USA | B4: FY27 | C4: =VLOOKUP(A4&B4,'Country P&L Forecast'!A4:J12,10,FALSE) -> 131146.42 | D4: ='Country BS Forecast'!D4-'Country BS Forecast'!D3 -> 7475.8562 | E4: ='Country BS Forecast'!E4-'Country BS Forecast'!E3 -> 5980.6849 | F4: ='Country BS Forecast'!F4-'Country BS Forecast'!F3 -> 2990.3425 | G4: ='Country P&L Forecast'!D4*Assumptions!$E$18 -> 101871 | H4: =C4-D4-E4+F4-G4 -> 18809.22 | I4: =C4*$P$2 -> 131146.42 | J4: =D4*$P$2 -> 7475.8562 | K4: =E4*$P$2 -> 5980.6849 | L4: =F4*$P$2 -> 2990.3425 | M4: =G4*$P$2 -> 101871 | O4: India | P4: =INDEX(Assumptions!$F:$F,MATCH(O4,Assumptions!$A:$A,0)) -> 0.012
A5: Germany | B5: FY25 | C5: =VLOOKUP(A5&B5,'Country P&L Forecast'!A5:J13,10,FALSE) -> 55269.2 | D5: ='Country BS Forecast'!D5-'Historical Data'!K7 -> 4265.7534 | E5: ='Country BS Forecast'!E5-'Historical Data'!L7 -> 3526.3562 | F5: ='Country BS Forecast'!F5-'Historical Data'!M7 -> 1763.1781 | G5: ='Country P&L Forecast'!D5*Assumptions!$E$19 -> 62972 | H5: =C5-D5-E5+F5-G5 -> -13731.732 | I5: =C5*$P$3 -> 50847.664 | J5: =D5*$P$3 -> 3924.4932 | K5: =E5*$P$3 -> 3244.2477 | L5: =F5*$P$3 -> 1622.1238 | M5: =G5*$P$3 -> 57934.24
A6: Germany | B6: FY26 | C6: =VLOOKUP(A6&B6,'Country P&L Forecast'!A6:J14,10,FALSE) -> 58039.968 | D6: ='Country BS Forecast'!D6-'Country BS Forecast'!D5 -> 4436.3836 | E6: ='Country BS Forecast'!E6-'Country BS Forecast'!E5 -> 3667.4104 | F6: ='Country BS Forecast'!F6-'Country BS Forecast'!F5 -> 1833.7052 | G6: ='Country P&L Forecast'!D6*Assumptions!$E$19 -> 65490.88 | H6: =C6-D6-E6+F6-G6 -> -13721.001 | I6: =C6*$P$3 -> 53396.771 | J6: =D6*$P$3 -> 4081.4729 | K6: =E6*$P$3 -> 3374.0176 | L6: =F6*$P$3 -> 1687.0088 | M6: =G6*$P$3 -> 60251.61
A7: Germany | B7: FY27 | C7: =VLOOKUP(A7&B7,'Country P&L Forecast'!A7:J15,10,FALSE) -> 60921.567 | D7: ='Country BS Forecast'!D7-'Country BS Forecast'!D6 -> 4613.8389 | E7: ='Country BS Forecast'!E7-'Country BS Forecast'!E6 -> 3814.1068 | F7: ='Country BS Forecast'!F7-'Country BS Forecast'!F6 -> 1907.0534 | G7: ='Country P&L Forecast'!D7*Assumptions!$E$19 -> 68110.515 | H7: =C7-D7-E7+F7-G7 -> -13709.841 | I7: =C7*$P$3 -> 56047.841 | J7: =D7*$P$3 -> 4244.7318 | K7: =E7*$P$3 -> 3508.9783 | L7: =F7*$P$3 -> 1754.4891 | M7: =G7*$P$3 -> 62661.674
A8: India | B8: FY25 | C8: =VLOOKUP(A8&B8,'Country P&L Forecast'!A8:J16,10,FALSE) -> 261000 | D8: ='Country BS Forecast'!D8-'Historical Data'!K10 -> 13808.219 | E8: ='Country BS Forecast'!E8-'Historical Data'!L10 -> 10126.027 | F8: ='Country BS Forecast'!F8-'Historical Data'!M10 -> 5063.0137 | G8: ='Country P&L Forecast'!D8*Assumptions!$E$20 -> 151200 | H8: =C8-D8-E8+F8-G8 -> 90928.767 | I8: =C8*$P$4 -> 3132 | J8: =D8*$P$4 -> 165.69863 | K8: =E8*$P$4 -> 121.51233 | L8: =F8*$P$4 -> 60.756164 | M8: =G8*$P$4 -> 1814.4
A9: India | B9: FY26 | C9: =VLOOKUP(A9&B9,'Country P&L Forecast'!A9:J17,10,FALSE) -> 283680 | D9: ='Country BS Forecast'!D9-'Country BS Forecast'!D8 -> 14912.877 | E9: ='Country BS Forecast'!E9-'Country BS Forecast'!E8 -> 10936.11 | F9: ='Country BS Forecast'!F9-'Country BS Forecast'!F8 -> 5468.0548 | G9: ='Country P&L Forecast'!D9*Assumptions!$E$20 -> 163296 | H9: =C9-D9-E9+F9-G9 -> 100003.07 | I9: =C9*$P$4 -> 3404.16 | J9: =D9*$P$4 -> 178.95452 | K9: =E9*$P$4 -> 131.23332 | L9: =F9*$P$4 -> 65.616658 | M9: =G9*$P$4 -> 1959.552
A10: India | B10: FY27 | C10: =VLOOKUP(A10&B10,'Country P&L Forecast'!A10:J18,10,FALSE) -> 308174.4 | D10: ='Country BS Forecast'!D10-'Country BS Forecast'!D9 -> 16105.907 | E10: ='Country BS Forecast'!E10-'Country BS Forecast'!E9 -> 11810.998 | F10: ='Country BS Forecast'!F10-'Country BS Forecast'!F9 -> 5905.4992 | G10: ='Country P&L Forecast'!D10*Assumptions!$E$20 -> 176359.68 | H10: =C10-D10-E10+F10-G10 -> 109803.31 | I10: =C10*$P$4 -> 3698.0928 | J10: =D10*$P$4 -> 193.27088 | K10: =E10*$P$4 -> 141.73198 | L10: =F10*$P$4 -> 70.86599 | M10: =G10*$P$4 -> 2116.3162

Sheet Consolidation
A1: Metric | B1: FY25 (USD) | C1: FY26 (USD) | D1: FY27 (USD) | F1: Country | G1: FX_to_USD
A2: Net Income | B2: =SUM('Country CashFlow Forecast'!I2,'Country CashFlow Forecast'!I5,'Country CashFlow Forecast'!I8) -> 171097.16 | C2: =SUM('Country CashFlow Forecast'!I3,'Country CashFlow Forecast'!I6,'Country CashFlow Forecast'!I9) -> 180761.81 | D2: =SUM('Country CashFlow Forecast'!I4,'Country CashFlow Forecast'!I7,'Country CashFlow Forecast'!I10) -> 190892.35 | F2: USA | G2: =INDEX(Assumptions!$F:$F,MATCH(F2,Assumptions!$A:$A,0)) -> 1
A3: Change in AR | B3: =SUM('Country CashFlow Forecast'!J2,'Country CashFlow Forecast'!J5,'Country CashFlow Forecast'!J8) -> 10871.014 | C3: =SUM('Country CashFlow Forecast'!J3,'Country CashFlow Forecast'!J6,'Country CashFlow Forecast'!J9) -> 11380.29 | D3: =SUM('Country CashFlow Forecast'!J4,'Country CashFlow Forecast'!J7,'Country CashFlow Forecast'!J10) -> 11913.859 | F3: Germany | G3: =INDEX(Assumptions!$F:$F,MATCH(F3,Assumptions!$A:$A,0)) -> 0.92
A4: Change in Inventory | B4: =SUM('Country CashFlow Forecast'!K2,'Country CashFlow Forecast'!K5,'Country CashFlow Forecast'!K8) -> 8790.4175 | C4: =SUM('Country CashFlow Forecast'!K3,'Country CashFlow Forecast'!K6,'Country CashFlow Forecast'!K9) -> 9201.1413 | D4: =SUM('Country CashFlow Forecast'!K4,'Country CashFlow Forecast'!K7,'Country CashFlow Forecast'!K10) -> 9631.3952 | F4: India | G4: =INDEX(Assumptions!$F:$F,MATCH(F4,Assumptions!$A:$A,0)) -> 0.012
A5: Change in AP | B5: =SUM('Country CashFlow Forecast'!L2,'Country CashFlow Forecast'!L5,'Country CashFlow Forecast'!L8) -> 4395.2088 | C5: =SUM('Country CashFlow Forecast'!L3,'Country CashFlow Forecast'!L6,'Country CashFlow Forecast'!L9) -> 4600.5707 | D5: =SUM('Country CashFlow Forecast'!L4,'Country CashFlow Forecast'!L7,'Country CashFlow Forecast'!L10) -> 4815.6976
A6: CapEx | B6: =SUM('Country CashFlow Forecast'!M2,'Country CashFlow Forecast'!M5,'Country CashFlow Forecast'!M8) -> 152148.64 | C6: =SUM('Country CashFlow Forecast'!M3,'Country CashFlow Forecast'!M6,'Country CashFlow Forecast'!M9) -> 159231.16 | D6: =SUM('Country CashFlow Forecast'!M4,'Country CashFlow Forecast'!M7,'Country CashFlow Forecast'!M10) -> 166648.99
A7: Net Cash Flow | B7: =B2-B3-B4+B5-B6 -> 3682.3015 | C7: =C2-C3-C4+C5-C6 -> 5549.7829 | D7: =D2-D3-D4+D5-D6 -> 7513.8064

Sheet Scenario Analysis
A1: Metric | B1: Base FY25 | C1: Revenue Optimistic | D1: Revenue Pessimistic | E1: Opex Optimistic | F1: Opex Pessimistic | G1: COGS Optimistic | H1: COGS Pessimistic
A2: Net Income | B2: =SUM('Country CashFlow Forecast'!I2,'Country CashFlow Forecast'!I5,'Country CashFlow Forecast'!I8) -> 171097.16 | C2: =B2*Assumptions!$B$24 -> 179652.02 | D2: =B2*Assumptions!$B$25 -> 162542.31 | E2: =B2*Assumptions!$C$24 -> 162542.31 | F2: =B2*Assumptions!$C$25 -> 179652.02 | G2: =B2*Assumptions!$D$24 -> 167675.22 | H2: =B2*Assumptions!$D$25 -> 174519.11
A3: Change in AR | B3: =SUM('Country CashFlow Forecast'!J2,'Country CashFlow Forecast'!J5,'Country CashFlow Forecast'!J8) -> 10871.014 | C3: =B3*Assumptions!$B$24 -> 11414.564 | D3: =B3*Assumptions!$B$25 -> 10327.463 | E3: =B3*Assumptions!$C$24 -> 10327.463 | F3: =B3*Assumptions!$C$25 -> 11414.564 | G3: =B3*Assumptions!$D$24 -> 10653.593 | H3: =B3*Assumptions!$D$25 -> 11088.434
A4: Change in Inventory | B4: =SUM('Country CashFlow Forecast'!K2,'Country CashFlow Forecast'!K5,'Country CashFlow Forecast'!K8) -> 8790.4175 | C4: =B4*Assumptions!$B$24 -> 9229.9384 | D4: =B4*Assumptions!$B$25 -> 8350.8967 | E4: =B4*Assumptions!$C$24 -> 8350.8967 | F4: =B4*Assumptions!$C$25 -> 9229.9384 | G4: =B4*Assumptions!$D$24 -> 8614.6092 | H4: =B4*Assumptions!$D$25 -> 8966.2259
A5: Change in AP | B5: =SUM('Country CashFlow Forecast'!L2,'Country CashFlow Forecast'!L5,'Country CashFlow Forecast'!L8) -> 4395.2088 | C5: =B5*Assumptions!$B$24 -> 4614.9692 | D5: =B5*Assumptions!$B$25 -> 4175.4483 | E5: =B5*Assumptions!$C$24 -> 4175.4483 | F5: =B5*Assumptions!$C$25 -> 4614.9692 | G5: =B5*Assumptions!$D$24 -> 4307.3046 | H5: =B5*Assumptions!$D$25 -> 4483.1129
A6: CapEx | B6: =SUM('Country CashFlow Forecast'!M2,'Country CashFlow Forecast'!M5,'Country CashFlow Forecast'!M8) -> 152148.64 | C6: 152148.64 | D6: 152148.64 | E6: 152148.64 | F6: 152148.64 | G6: 152148.64 | H6: 152148.64
A7: Net Cash Flow | B7: =B2-B3-B4+B5-B6 -> 3682.3015 | C7: =C2-C3-C4+C5-C6 -> 11473.849 | D7: =D2-D3-D4+D5-D6 -> -4109.2455 | E7: =E2-E3-E4+E5-E6 -> -4109.2455 | F7: =F2-F3-F4+F5-F6 -> 11473.849 | G7: =G2-G3-G4+G5-G6 -> 565.6827 | H7: =H2-H3-H4+H5-H6 -> 6798.9204
A9: Metric | B9: Base FY26 | C9: Revenue Optimistic | D9: Revenue Pessimistic | E9: Opex Optimistic | F9: Opex Pessimistic | G9: COGS Optimistic | H9: COGS Pessimistic
A10: Net Income | B10: 180761.81 | C10: =B10*Assumptions!$B$24 -> 189799.9 | D10: =B10*Assumptions!$B$25 -> 171723.72 | E10: =B10*Assumptions!$C$24 -> 171723.72 | F10: =B10*Assumptions!$C$25 -> 189799.9 | G10: =B10*Assumptions!$D$24 -> 177146.57 | H10: =B10*Assumptions!$D$25 -> 184377.04
A11: Change in AR | B11: 11380.29 | C11: =B11*Assumptions!$B$24 -> 11949.305 | D11: =B11*Assumptions!$B$25 -> 10811.276 | E11: =B11*Assumptions!$C$24 -> 10811.276 | F11: =B11*Assumptions!$C$25 -> 11949.305 | G11: =B11*Assumptions!$D$24 -> 11152.685 | H11: =B11*Assumptions!$D$25 -> 11607.896
A12: Change in Inventory | B12: 9201.1413 | C12: =B12*Assumptions!$B$24 -> 9661.1984 | D12: =B12*Assumptions!$B$25 -> 8741.0842 | E12: =B12*Assumptions!$C$24 -> 8741.0842 | F12: =B12*Assumptions!$C$25 -> 9661.1984 | G12: =B12*Assumptions!$D$24 -> 9017.1185 | H12: =B12*Assumptions!$D$25 -> 9385.1641
A13: Change in AP | B13: 4600.5707 | C13: =B13*Assumptions!$B$24 -> 4830.5992 | D13: =B13*Assumptions!$B$25 -> 4370.5421 | E13: =B13*Assumptions!$C$24 -> 4370.5421 | F13: =B13*Assumptions!$C$25 -> 4830.5992 | G13: =B13*Assumptions!$D$24 -> 4508.5592 | H13: =B13*Assumptions!$D$25 -> 4692.5821
A14: CapEx | B14: 159231.16 | C14: 159231.16 | D14: 159231.16 | E14: 159231.16 | F14: 159231.16 | G14: 159231.16 | H14: 159231.16
A15: Net Cash Flow | B15: =B10-B11-B12+B13-B14 -> 5549.7829 | C15: =C10-C11-C12+C13-C14 -> 13788.83 | D15: =D10-D11-D12+D13-D14 -> -2689.2643 | E15: =E10-E11-E12+E13-E14 -> -2689.2643 | F15: =F10-F11-F12+F13-F14 -> 13788.83 | G15: =G10-G11-G12+G13-G14 -> 2254.164 | H15: =H10-H11-H12+H13-H14 -> 8845.4018
A17: Metric | B17: Base FY27 | C17: Revenue Optimistic | D17: Revenue Pessimistic | E17: Opex Optimistic | F17: Opex Pessimistic | G17: COGS Optimistic | H17: COGS Pessimistic
A18: Net Income | B18: 190892.35 | C18: =B18*Assumptions!$B$24 -> 200436.97 | D18: =B18*Assumptions!$B$25 -> 181347.74 | E18: =B18*Assumptions!$C$24 -> 181347.74 | F18: =B18*Assumptions!$C$25 -> 200436.97 | G18: =B18*Assumptions!$D$24 -> 187074.51 | H18: =B18*Assumptions!$D$25 -> 194710.2
A19: Change in AR | B19: 11913.859 | C19: =B19*Assumptions!$B$24 -> 12509.552 | D19: =B19*Assumptions!$B$25 -> 11318.166 | E19: =B19*Assumptions!$C$24 -> 11318.166 | F19: =B19*Assumptions!$C$25 -> 12509.552 | G19: =B19*Assumptions!$D$24 -> 11675.582 | H19: =B19*Assumptions!$D$25 -> 12152.136
A20: Change in Inventory | B20: 9631.3952 | C20: =B20*Assumptions!$B$24 -> 10112.965 | D20: =B20*Assumptions!$B$25 -> 9149.8254 | E20: =B20*Assumptions!$C$24 -> 9149.8254 | F20: =B20*Assumptions!$C$25 -> 10112.965 | G20: =B20*Assumptions!$D$24 -> 9438.7673 | H20: =B20*Assumptions!$D$25 -> 9824.0231
A21: Change in AP | B21: 4815.6976 | C21: =B21*Assumptions!$B$24 -> 5056.4825 | D21: =B21*Assumptions!$B$25 -> 4574.9127 | E21: =B21*Assumptions!$C$24 -> 4574.9127 | F21: =B21*Assumptions!$C$25 -> 5056.4825 | G21: =B21*Assumptions!$D$24 -> 4719.3836 | H21: =B21*Assumptions!$D$25 -> 4912.0115
A22: CapEx | B22: 166648.99 | C22: 166648.99 | D22: 166648.99 | E22: 166648.99 | F22: 166648.99 | G22: 166648.99 | H22: 166648.99
A23: Net Cash Flow | B23: =B18-B19-B20+B21-B22 -> 7513.8064 | C23: =C18-C19-C20+C21-C22 -> 16221.946 | D23: =D18-D19-D20+D21-D22 -> -1194.3335 | E23: =E18-E19-E20+E21-E22 -> -1194.3335 | F23: =F18-F19-F20+F21-F22 -> 16221.946 | G23: =G18-G19-G20+G21-G22 -> 4030.5504 | H23: =H18-H19-H20+H21-H22 -> 10997.062

Sheet Sensitivity Table
A1: Sensitivity Analysis
A2: FY25 Driver | B2: –5% | C2: –2% | D2: Base | E2: 0.02 | F2: 0.05 | G2: -0.05 | H2: –2% | I2: 0.02 | J2: 0.05
A3: Revenue % | B3: =D3*G3 -> 162542.15 | C3: =D3*H3 -> 167675.06 | D3: 171097 | E3: =D3*I3 -> 174518.94 | F3: =D3*J3 -> 179651.85 | G3: =1-0.05 -> 0.95 | H3: =1-0.02 -> 0.98 | I3: =1+0.02 -> 1.02 | J3: =1+0.05 -> 1.05
A4: OPEX % | B4: =D4*G4 -> 179651.85 | C4: =D4*H4 -> 174518.94 | D4: 171097 | E4: =D4*I4 -> 167675.06 | F4: =D4*J4 -> 162542.15 | G4: =1+0.05 -> 1.05 | H4: =1+0.02 -> 1.02 | I4: =1-0.02 -> 0.98 | J4: =1-0.05 -> 0.95
A5: COGS % | B5: =D5*G5 -> 179652.9 | C5: =D5*H5 -> 174519.96 | D5: 171098 | E5: =D5*I5 -> 167676.04 | F5: =D5*J5 -> 162543.1 | G5: =1+0.05 -> 1.05 | H5: =1+0.02 -> 1.02 | I5: =1-0.02 -> 0.98 | J5: =1-0.05 -> 0.95
A7: FY26 Driver | B7: –5% | C7: –2% | D7: Base | E7: 0.02 | F7: 0.05
A8: Revenue % | B8: =$D$8*G3 -> 171723.72 | C8: =$D$8*H3 -> 177146.57 | D8: 180761.81 | E8: =$D$8*I3 -> 184377.04 | F8: =$D$8*J3 -> 189799.9
A9: OPEX % | B9: =$D$8*G4 -> 189799.9 | C9: =$D$8*H4 -> 184377.04 | D9: 180761.81 | E9: =$D$8*I4 -> 177146.57 | F9: =$D$8*J4 -> 171723.72
A10: COGS % | B10: =$D$8*G5 -> 189799.9 | C10: =$D$8*H5 -> 184377.04 | D10: 180761.81 | E10: =$D$8*I5 -> 177146.57 | F10: =$D$8*J5 -> 171723.72
A12: FY27 Driver | B12: –5% | C12: –2% | D12: Base | E12: 0.02 | F12: 0.05
A13: Revenue % | B13: =$D13*G3 -> 181347.74 | C13: =$D13*H3 -> 187074.51 | D13: 190892.35 | E13: =$D13*I3 -> 194710.2 | F13: =$D13*J3 -> 200436.97
A14: OPEX % | B14: =$D14*G4 -> 200436.97 | C14: =$D14*H4 -> 194710.2 | D14: 190892.35 | E14: =$D14*I4 -> 187074.51 | F14: =$D14*J4 -> 181347.74
A15: COGS % | B15: =$D15*G5 -> 200436.97 | C15: =$D15*H5 -> 194710.2 | D15: 190892.35 | E15: =$D15*I5 -> 187074.51 | F15: =$D15*J5 -> 181347.74

Sheet Dashboard (Power BI preview)
A1: Jennika Thomas - Dashboard (Created in Power BI)
A3: Dashboard visualization created in Microsoft Power BI. Inserted for reference.
