Workbook

Sheet Dashboard
A1: Jennika Thomas | B1: Variance Analysis Dashboard
A3: YTD Revenue Var % | B3: =(SUM('Raw Data'!C2:C13)-SUM('Raw Data'!B2:B13))/SUM('Raw Data'!B2:B13) -> -0.017971014
A4: YTD OPEX Var % | B4: =(SUM('Raw Data'!E2:E13)-SUM('Raw Data'!D2:D13))/SUM('Raw Data'!D2:D13) -> -0.0085158151
A5: YTD EBITDA Var % | B5: =(SUM('Raw Data'!G2:G13)-SUM('Raw Data'!F2:F13))/SUM('Raw Data'!F2:F13) -> -0.026578073

Sheet Raw Data
A1: Month | B1: Revenue Budget | C1: Revenue Actual | D1: OPEX Budget | E1: OPEX Actual | F1: EBITDA Budget | G1: EBITDA Actual
A2: Jan | B2: 100000 | C2: 95000 | D2: 60000 | E2: 58000 | F2: 40000 | G2: 37000
A3: Feb | B3: 120000 | C3: 118000 | D3: 65000 | E3: 67000 | F3: 55000 | G3: 51000
A4: Mar | B4: 130000 | C4: 128000 | D4: 64000 | E4: 65000 | F4: 66000 | G4: 63000
A5: Apr | B5: 125000 | C5: 115000 | D5: 63000 | E5: 61000 | F5: 62000 | G5: 54000
A6: May | B6: 140000 | C6: 132000 | D6: 66000 | E6: 65000 | F6: 74000 | G6: 67000
A7: Jun | B7: 135000 | C7: 130000 | D7: 68000 | E7: 66000 | F7: 67000 | G7: 64000
A8: Jul | B8: 150000 | C8: 148000 | D8: 70000 | E8: 70500 | F8: 80000 | G8: 77500
A9: Aug | B9: 155000 | C9: 158000 | D9: 72000 | E9: 71000 | F9: 83000 | G9: 87000
A10: Sep | B10: 160000 | C10: 158000 | D10: 71000 | E10: 70000 | F10: 89000 | G10: 88000
A11: Oct | B11: 170000 | C11: 172000 | D11: 73000 | E11: 72500 | F11: 97000 | G11: 99500
A12: Nov | B12: 165000 | C12: 160000 | D12: 74000 | E12: 73500 | F12: 91000 | G12: 86500
A13: Dec | B13: 175000 | C13: 180000 | D13: 76000 | E13: 75500 | F13: 99000 | G13: 104500

Sheet Calculations
A1: Month | B1: Revenue Variance | C1: Revenue Variance % | D1: OPEX Variance | E1: OPEX Variance % | F1: EBITDA Variance | G1: EBITDA Variance %
A2: Jan | B2: ='Raw Data'!C2-'Raw Data'!B2 -> -5000 | C2: =IF('Raw Data'!B2=0,0,('Raw Data'!C2-'Raw Data'!B2)/'Raw Data'!B2) -> -0.05 | D2: ='Raw Data'!E2-'Raw Data'!D2 -> -2000 | E2: =IF('Raw Data'!D2=0,0,('Raw Data'!E2-'Raw Data'!D2)/'Raw Data'!D2) -> -0.033333333 | F2: ='Raw Data'!G2-'Raw Data'!F2 -> -3000 | G2: =IF('Raw Data'!F2=0,0,('Raw Data'!G2-'Raw Data'!F2)/'Raw Data'!F2) -> -0.075
A3: Feb | B3: ='Raw Data'!C3-'Raw Data'!B3 -> -2000 | C3: =IF('Raw Data'!B3=0,0,('Raw Data'!C3-'Raw Data'!B3)/'Raw Data'!B3) -> -0.016666667 | D3: ='Raw Data'!E3-'Raw Data'!D3 -> 2000 | E3: =IF('Raw Data'!D3=0,0,('Raw Data'!E3-'Raw Data'!D3)/'Raw Data'!D3) -> 0.030769231 | F3: ='Raw Data'!G3-'Raw Data'!F3 -> -4000 | G3: =IF('Raw Data'!F3=0,0,('Raw Data'!G3-'Raw Data'!F3)/'Raw Data'!F3) -> -0.072727273
A4: Mar | B4: ='Raw Data'!C4-'Raw Data'!B4 -> -2000 | C4: =IF('Raw Data'!B4=0,0,('Raw Data'!C4-'Raw Data'!B4)/'Raw Data'!B4) -> -0.015384615 | D4: ='Raw Data'!E4-'Raw Data'!D4 -> 1000 | E4: =IF('Raw Data'!D4=0,0,('Raw Data'!E4-'Raw Data'!D4)/'Raw Data'!D4) -> 0.015625 | F4: ='Raw Data'!G4-'Raw Data'!F4 -> -3000 | G4: =IF('Raw Data'!F4=0,0,('Raw Data'!G4-'Raw Data'!F4)/'Raw Data'!F4) -> -0.045454545
A5: Apr | B5: ='Raw Data'!C5-'Raw Data'!B5 -> -10000 | C5: =IF('Raw Data'!B5=0,0,('Raw Data'!C5-'Raw Data'!B5)/'Raw Data'!B5) -> -0.08 | D5: ='Raw Data'!E5-'Raw Data'!D5 -> -2000 | E5: =IF('Raw Data'!D5=0,0,('Raw Data'!E5-'Raw Data'!D5)/'Raw Data'!D5) -> -0.031746032 | F5: ='Raw Data'!G5-'Raw Data'!F5 -> -8000 | G5: =IF('Raw Data'!F5=0,0,('Raw Data'!G5-'Raw Data'!F5)/'Raw Data'!F5) -> -0.12903226
A6: May | B6: ='Raw Data'!C6-'Raw Data'!B6 -> -8000 | C6: =IF('Raw Data'!B6=0,0,('Raw Data'!C6-'Raw Data'!B6)/'Raw Data'!B6) -> -0.057142857 | D6: ='Raw Data'!E6-'Raw Data'!D6 -> -1000 | E6: =IF('Raw Data'!D6=0,0,('Raw Data'!E6-'Raw Data'!D6)/'Raw Data'!D6) -> -0.015151515 | F6: ='Raw Data'!G6-'Raw Data'!F6 -> -7000 | G6: =IF('Raw Data'!F6=0,0,('Raw Data'!G6-'Raw Data'!F6)/'Raw Data'!F6) -> -0.094594595
A7: Jun | B7: ='Raw Data'!C7-'Raw Data'!B7 -> -5000 | C7: =IF('Raw Data'!B7=0,0,('Raw Data'!C7-'Raw Data'!B7)/'Raw Data'!B7) -> -0.037037037 | D7: ='Raw Data'!E7-'Raw Data'!D7 -> -2000 | E7: =IF('Raw Data'!D7=0,0,('Raw Data'!E7-'Raw Data'!D7)/'Raw Data'!D7) -> -0.029411765 | F7: ='Raw Data'!G7-'Raw Data'!F7 -> -3000 | G7: =IF('Raw Data'!F7=0,0,('Raw Data'!G7-'Raw Data'!F7)/'Raw Data'!F7) -> -0.044776119
A8: Jul | B8: ='Raw Data'!C8-'Raw Data'!B8 -> -2000 | C8: =IF('Raw Data'!B8=0,0,('Raw Data'!C8-'Raw Data'!B8)/'Raw Data'!B8) -> -0.013333333 | D8: ='Raw Data'!E8-'Raw Data'!D8 -> 500 | E8: =IF('Raw Data'!D8=0,0,('Raw Data'!E8-'Raw Data'!D8)/'Raw Data'!D8) -> 0.0071428571 | F8: ='Raw Data'!G8-'Raw Data'!F8 -> -2500 | G8: =IF('Raw Data'!F8=0,0,('Raw Data'!G8-'Raw Data'!F8)/'Raw Data'!F8) -> -0.03125
A9: Aug | B9: ='Raw Data'!C9-'Raw Data'!B9 -> 3000 | C9: =IF('Raw Data'!B9=0,0,('Raw Data'!C9-'Raw Data'!B9)/'Raw Data'!B9) -> 0.019354839 | D9: ='Raw Data'!E9-'Raw Data'!D9 -> -1000 | E9: =IF('Raw Data'!D9=0,0,('Raw Data'!E9-'Raw Data'!D9)/'Raw Data'!D9) -> -0.013888889 | F9: ='Raw Data'!G9-'Raw Data'!F9 -> 4000 | G9: =IF('Raw Data'!F9=0,0,('Raw Data'!G9-'Raw Data'!F9)/'Raw Data'!F9) -> 0.048192771
A10: Sep | B10: ='Raw Data'!C10-'Raw Data'!B10 -> -2000 | C10: =IF('Raw Data'!B10=0,0,('Raw Data'!C10-'Raw Data'!B10)/'Raw Data'!B10) -> -0.0125 | D10: ='Raw Data'!E10-'Raw Data'!D10 -> -1000 | E10: =IF('Raw Data'!D10=0,0,('Raw Data'!E10-'Raw Data'!D10)/'Raw Data'!D10) -> -0.014084507 | F10: ='Raw Data'!G10-'Raw Data'!F10 -> -1000 | G10: =IF('Raw Data'!F10=0,0,('Raw Data'!G10-'Raw Data'!F10)/'Raw Data'!F10) -> -0.011235955
A11: Oct | B11: ='Raw Data'!C11-'Raw Data'!B11 -> 2000 | C11: =IF('Raw Data'!B11=0,0,('Raw Data'!C11-'Raw Data'!B11)/'Raw Data'!B11) -> 0.011764706 | D11: ='Raw Data'!E11-'Raw Data'!D11 -> -500 | E11: =IF('Raw Data'!D11=0,0,('Raw Data'!E11-'Raw Data'!D11)/'Raw Data'!D11) -> -0.0068493151 | F11: ='Raw Data'!G11-'Raw Data'!F11 -> 2500 | G11: =IF('Raw Data'!F11=0,0,('Raw Data'!G11-'Raw Data'!F11)/'Raw Data'!F11) -> 0.025773196
A12: Nov | B12: ='Raw Data'!C12-'Raw Data'!B12 -> -5000 | C12: =IF('Raw Data'!B12=0,0,('Raw Data'!C12-'Raw Data'!B12)/'Raw Data'!B12) -> -0.03030303 | D12: ='Raw Data'!E12-'Raw Data'!D12 -> -500 | E12: =IF('Raw Data'!D12=0,0,('Raw Data'!E12-'Raw Data'!D12)/'Raw Data'!D12) -> -0.0067567568 | F12: ='Raw Data'!G12-'Raw Data'!F12 -> -4500 | G12: =IF('Raw Data'!F12=0,0,('Raw Data'!G12-'Raw Data'!F12)/'Raw Data'!F12) -> -0.049450549
A13: Dec | B13: ='Raw Data'!C13-'Raw Data'!B13 -> 5000 | C13: =IF('Raw Data'!B13=0,0,('Raw Data'!C13-'Raw Data'!B13)/'Raw Data'!B13) -> 0.028571429 | D13: ='Raw Data'!E13-'Raw Data'!D13 -> -500 | E13: =IF('Raw Data'!D13=0,0,('Raw Data'!E13-'Raw Data'!D13)/'Raw Data'!D13) -> -0.0065789474 | F13: ='Raw Data'!G13-'Raw Data'!F13 -> 5500 | G13: =IF('Raw Data'!F13=0,0,('Raw Data'!G13-'Raw Data'!F13)/'Raw Data'!F13) -> 0.055555556
